[{"description":"OpenTable clone","fullName":"KoKo-debug/OpenPlayful","license":{"key":"","name":"","url":""},"stargazersCount":8,"updatedAt":"2020-02-06T18:14:50Z","url":"https://github.com/KoKo-debug/OpenPlayful"},{"description":"An openTable Clone","fullName":"jerryzlau/OpenRice","license":{"key":"","name":"","url":""},"stargazersCount":4,"updatedAt":"2020-08-17T03:33:04Z","url":"https://github.com/jerryzlau/OpenRice"},{"description":"An OpenTable clone!","fullName":"sophiacheungshc/kitchen_fable","license":{"key":"","name":"","url":""},"stargazersCount":4,"updatedAt":"2019-09-29T00:58:30Z","url":"https://github.com/sophiacheungshc/kitchen_fable"},{"description":"Table is an OpenTable clone, built with React and Rails","fullName":"RowiDont/Table","license":{"key":"mit","name":"MIT License","url":"https://api.github.com/licenses/mit"},"stargazersCount":3,"updatedAt":"2022-03-12T09:34:02Z","url":"https://github.com/RowiDont/Table"},{"description":"An OpenTable clone written with @ashbt to learn Rails.","fullName":"jbinto/seatyourself","license":{"key":"","name":"","url":""},"stargazersCount":1,"updatedAt":"2016-01-18T22:34:39Z","url":"https://github.com/jbinto/seatyourself"},{"description":"OpenTable clone","fullName":"samirremtulla/SamirTable","license":{"key":"","name":"","url":""},"stargazersCount":1,"updatedAt":"2015-06-03T22:08:33Z","url":"https://github.com/samirremtulla/SamirTable"},{"description":"OpenTable clone","fullName":"aspn/nomnom","license":{"key":"","name":"","url":""},"stargazersCount":1,"updatedAt":"2015-06-03T22:09:58Z","url":"https://github.com/aspn/nomnom"},{"description":"OpenTable Clone","fullName":"JuhaMikkola/seat_yourself","license":{"key":"","name":"","url":""},"stargazersCount":1,"updatedAt":"2017-08-02T18:59:57Z","url":"https://github.com/JuhaMikkola/seat_yourself"},{"description":"OpenTable clone","fullName":"Skulllady/closeTable","license":{"key":"","name":"","url":""},"stargazersCount":1,"updatedAt":"2021-10-14T17:17:25Z","url":"https://github.com/Skulllady/closeTable"},{"description":"OpenTable clone using Rails","fullName":"elvingm/reservester","license":{"key":"","name":"","url":""},"stargazersCount":1,"updatedAt":"2023-03-04T05:24:18Z","url":"https://github.com/elvingm/reservester"},{"description":"Restaurant reservation project using next 13 ","fullName":"the-kamol/opentable-clone","license":{"key":"","name":"","url":""},"stargazersCount":1,"updatedAt":"2025-04-29T09:53:13Z","url":"https://github.com/the-kamol/opentable-clone"},{"description":"","fullName":"DennohKim/opentable-clone","license":{"key":"","name":"","url":""},"stargazersCount":1,"updatedAt":"2023-03-08T18:48:45Z","url":"https://github.com/DennohKim/opentable-clone"},{"description":"Effort to make OpenTable clone","fullName":"kashyap-bhatt15/reservester","license":{"key":"","name":"","url":""},"stargazersCount":1,"updatedAt":"2013-12-16T19:21:19Z","url":"https://github.com/kashyap-bhatt15/reservester"},{"description":"opentable clone project for learning next.js framework","fullName":"blowecle/opentable","license":{"key":"","name":"","url":""},"stargazersCount":1,"updatedAt":"2023-07-24T21:51:47Z","url":"https://github.com/blowecle/opentable"},{"description":"A node.js OpenTable clone built with Express and Backbone","fullName":"nerdgrass/rsrv","license":{"key":"","name":"","url":""},"stargazersCount":1,"updatedAt":"2017-08-02T18:59:05Z","url":"https://github.com/nerdgrass/rsrv"},{"description":"Bitmaker Assignment - OpenTable Clone","fullName":"Lazigerbill/seat_yourself","license":{"key":"","name":"","url":""},"stargazersCount":0,"updatedAt":"2016-08-02T14:36:42Z","url":"https://github.com/Lazigerbill/seat_yourself"},{"description":"","fullName":"cloudzeus/opentableClone","license":{"key":"","name":"","url":""},"stargazersCount":0,"updatedAt":"2023-04-18T05:33:05Z","url":"https://github.com/cloudzeus/opentableClone"},{"description":"","fullName":"ravidindi/OpentableClone","license":{"key":"","name":"","url":""},"stargazersCount":0,"updatedAt":"2023-12-23T10:31:58Z","url":"https://github.com/ravidindi/OpentableClone"},{"description":"","fullName":"syedshehmeer/OpentableClone","license":{"key":"","name":"","url":""},"stargazersCount":0,"updatedAt":"2023-09-17T01:29:59Z","url":"https://github.com/syedshehmeer/OpentableClone"},{"description":"OpenTable clone ","fullName":"codycc/seatyourself","license":{"key":"","name":"","url":""},"stargazersCount":0,"updatedAt":"2016-03-24T23:03:58Z","url":"https://github.com/codycc/seatyourself"}]
